DensityClust/LocalDensityClustering_main.py
DensityClust/__init__.py
DensityClust/clustring_subfunc.py
DensityClust/localDenClust2.py
DensityClust/split_cube.py
Generate/__init__.py
Generate/fits_header.py
Generate/generate.py
Generate/synthetic_data.py
LDC_MGM_main/LDC_MGM_main.py
LDC_MGM_main/LDC_main.py
LDC_MGM_main/LDC_mian.py
LDC_MGM_main/__init__.py
fit_clump_function/__init__.py
fit_clump_function/main_fit_gauss_3d.py
fit_clump_function/multi_gauss_fitting_new.py
fit_clump_function/touch_clump.py
t_match/__init__.py
t_match/match_6_.py
tools/__init__.py
tools/data_merge.py
tools/identify_plot_711.py
tools/make_plot.py
tools/show_clumps.py
tools/ultil_lxy.py
DensityClust-1.4.9.dist-info/METADATA
DensityClust-1.4.9.dist-info/WHEEL
DensityClust-1.4.9.dist-info/top_level.txt
DensityClust-1.4.9.dist-info/RECORD
