Metadata-Version: 2.1
Name: DensityClust
Version: 1.4.9
Summary: Molecular Clump extraction algorithm based on Local Density Clustering*
Home-page: https://github.com/Luoxiaoyu828/LDC-MGM
Author: Luo Xiaoyu
Author-email: vastlxy@163.com
License: UNKNOWN
Project-URL: Bug Tracker, https://github.com/Luoxiaoyu828/LDC_MGM/issues
Platform: UNKNOWN
